{
  "plugins": [
    "react",
    "import"
  ],
  "rules": {
    "react/forbid-elements": [
      "warn",
      {
        "forbid": []
      }
    ],
    "no-restricted-imports": [
      "warn",
      {
        "patterns": [
          {
            "group": [
              "components/brand/**",
              "components/core/**",
              "components/forms/**",
              "ui_kits/app/**",
              "ui_kits/website/**"
            ],
            "message": "Import design-system components from 'index.js', not component internals."
          }
        ]
      }
    ],
    "no-restricted-syntax": [
      "warn",
      {
        "selector": "Literal[value=/#[0-9a-fA-F]{3,8}\\b/]",
        "message": "Raw hex color — use a design-system color token via var()."
      },
      {
        "selector": "Literal[value=/\\b\\d+px\\b/]",
        "message": "Raw px value — use a design-system spacing token via var()."
      },
      {
        "selector": "Literal[value=/font-family\\s*:\\s*(?!['\\\"]?(?:Oswald|Mulish|Lora))/i]",
        "message": "Font not provided by the design system. Available: Oswald, Mulish, Lora."
      },
      {
        "selector": "JSXOpeningElement[name.name='Badge'] > JSXAttribute > JSXIdentifier[name!=/^(?:children|tone|soft|dot|style|key|ref|className|style|children)$/]",
        "message": "<Badge> doesn't accept that prop. Declared props: children, tone, soft, dot, style."
      },
      {
        "selector": "JSXOpeningElement[name.name='Badge'] > JSXAttribute[name.name='tone'] > Literal[value!=/^(?:cyan|emerald|aqua|ocean|navy|success|warning)$/]",
        "message": "<Badge> tone must be one of 'cyan' | 'emerald' | 'aqua' | 'ocean' | 'navy' | 'success' | 'warning'."
      },
      {
        "selector": "JSXOpeningElement[name.name='Button'] > JSXAttribute > JSXIdentifier[name!=/^(?:children|variant|size|iconLeft|iconRight|full|disabled|type|onClick|style|key|ref|className|style|children)$/]",
        "message": "<Button> doesn't accept that prop. Declared props: children, variant, size, iconLeft, iconRight, full, disabled, type, onClick, style."
      },
      {
        "selector": "JSXOpeningElement[name.name='Button'] > JSXAttribute[name.name='variant'] > Literal[value!=/^(?:primary|secondary|outline|ghost|deep)$/]",
        "message": "<Button> variant must be one of 'primary' | 'secondary' | 'outline' | 'ghost' | 'deep'."
      },
      {
        "selector": "JSXOpeningElement[name.name='Button'] > JSXAttribute[name.name='size'] > Literal[value!=/^(?:sm|md|lg)$/]",
        "message": "<Button> size must be one of 'sm' | 'md' | 'lg'."
      },
      {
        "selector": "JSXOpeningElement[name.name='Button'] > JSXAttribute[name.name='type'] > Literal[value!=/^(?:button|submit|reset)$/]",
        "message": "<Button> type must be one of 'button' | 'submit' | 'reset'."
      },
      {
        "selector": "JSXOpeningElement[name.name='Card'] > JSXAttribute > JSXIdentifier[name!=/^(?:children|padding|accent|interactive|style|key|ref|className|style|children)$/]",
        "message": "<Card> doesn't accept that prop. Declared props: children, padding, accent, interactive, style."
      },
      {
        "selector": "JSXOpeningElement[name.name='Card'] > JSXAttribute[name.name='padding'] > Literal[value!=/^(?:none|sm|md|lg)$/]",
        "message": "<Card> padding must be one of 'none' | 'sm' | 'md' | 'lg'."
      },
      {
        "selector": "JSXOpeningElement[name.name='Input'] > JSXAttribute > JSXIdentifier[name!=/^(?:label|hint|error|iconLeft|type|id|placeholder|value|disabled|onChange|style|key|ref|className|style|children)$/]",
        "message": "<Input> doesn't accept that prop. Declared props: label, hint, error, iconLeft, type, id, placeholder, value, disabled, onChange, style."
      },
      {
        "selector": "JSXOpeningElement[name.name='Logo'] > JSXAttribute > JSXIdentifier[name!=/^(?:variant|size|tone|style|key|ref|className|style|children)$/]",
        "message": "<Logo> doesn't accept that prop. Declared props: variant, size, tone, style."
      },
      {
        "selector": "JSXOpeningElement[name.name='Logo'] > JSXAttribute[name.name='variant'] > Literal[value!=/^(?:mark|lockup|lockup-horizontal)$/]",
        "message": "<Logo> variant must be one of 'mark' | 'lockup' | 'lockup-horizontal'."
      },
      {
        "selector": "JSXOpeningElement[name.name='Logo'] > JSXAttribute[name.name='tone'] > Literal[value!=/^(?:navy|white)$/]",
        "message": "<Logo> tone must be one of 'navy' | 'white'."
      },
      {
        "selector": "JSXOpeningElement[name.name='WaveDivider'] > JSXAttribute > JSXIdentifier[name!=/^(?:fill|height|flip|gradient|style|key|ref|className|style|children)$/]",
        "message": "<WaveDivider> doesn't accept that prop. Declared props: fill, height, flip, gradient, style."
      }
    ]
  },
  "overrides": [
    {
      "files": [
        "**/index.js"
      ],
      "rules": {
        "no-restricted-imports": "off"
      }
    }
  ],
  "x-omelette": {
    "components": {
      "Badge": {
        "replaces": []
      },
      "Button": {
        "replaces": []
      },
      "Card": {
        "replaces": []
      },
      "Input": {
        "replaces": []
      },
      "Logo": {
        "replaces": []
      },
      "WaveDivider": {
        "replaces": []
      }
    },
    "tokens": [
      "--body-font",
      "--body-weight",
      "--border-focus",
      "--border-strong",
      "--border-subtle",
      "--color-accent",
      "--color-deep",
      "--color-primary",
      "--color-primary-active",
      "--color-primary-hover",
      "--color-secondary",
      "--color-secondary-hover",
      "--container-max",
      "--container-narrow",
      "--display-font",
      "--display-tracking",
      "--display-weight",
      "--dur-base",
      "--dur-fast",
      "--dur-slow",
      "--ease-out",
      "--ease-standard",
      "--eyebrow-font",
      "--fde-aqua",
      "--fde-aqua-50",
      "--fde-blue",
      "--fde-cyan",
      "--fde-cyan-100",
      "--fde-cyan-50",
      "--fde-cyan-600",
      "--fde-cyan-700",
      "--fde-danger",
      "--fde-emerald",
      "--fde-emerald-100",
      "--fde-emerald-50",
      "--fde-emerald-600",
      "--fde-gray-300",
      "--fde-gray-400",
      "--fde-info",
      "--fde-ink",
      "--fde-line",
      "--fde-mist",
      "--fde-navy",
      "--fde-ocean",
      "--fde-ocean-50",
      "--fde-ocean-700",
      "--fde-paper",
      "--fde-pine",
      "--fde-slate",
      "--fde-slate-700",
      "--fde-success",
      "--fde-warning",
      "--fde-white",
      "--font-accent",
      "--font-display",
      "--font-sans",
      "--fw-bold",
      "--fw-extra",
      "--fw-medium",
      "--fw-regular",
      "--fw-semibold",
      "--gradient-deep",
      "--gradient-wave",
      "--gradient-wave-soft",
      "--header-height",
      "--heading-font",
      "--heading-weight",
      "--leading-normal",
      "--leading-relaxed",
      "--leading-snug",
      "--leading-tight",
      "--quote-font",
      "--radius-2xl",
      "--radius-circle",
      "--radius-lg",
      "--radius-md",
      "--radius-pill",
      "--radius-sm",
      "--radius-xl",
      "--radius-xs",
      "--ring-focus",
      "--shadow-brand",
      "--shadow-lg",
      "--shadow-md",
      "--shadow-sm",
      "--shadow-xs",
      "--space-0",
      "--space-1",
      "--space-10",
      "--space-12",
      "--space-2",
      "--space-3",
      "--space-4",
      "--space-5",
      "--space-6",
      "--space-7",
      "--space-8",
      "--space-9",
      "--surface-brand",
      "--surface-card",
      "--surface-deep",
      "--surface-page",
      "--surface-sunken",
      "--text-2xl",
      "--text-3xl",
      "--text-4xl",
      "--text-5xl",
      "--text-6xl",
      "--text-base",
      "--text-body",
      "--text-heading",
      "--text-lg",
      "--text-link",
      "--text-md",
      "--text-muted",
      "--text-on-brand",
      "--text-sm",
      "--text-strong",
      "--text-xl",
      "--text-xs",
      "--tracking-caps",
      "--tracking-normal",
      "--tracking-tight",
      "--tracking-wide",
      "--tracking-wordmark"
    ],
    "tokenKinds": {
      "--fde-emerald": "color",
      "--fde-aqua": "color",
      "--fde-cyan": "color",
      "--fde-blue": "color",
      "--fde-ocean": "color",
      "--fde-pine": "color",
      "--fde-navy": "color",
      "--fde-emerald-50": "color",
      "--fde-aqua-50": "color",
      "--fde-cyan-50": "color",
      "--fde-ocean-50": "color",
      "--fde-cyan-100": "color",
      "--fde-emerald-100": "color",
      "--fde-cyan-600": "color",
      "--fde-cyan-700": "color",
      "--fde-emerald-600": "color",
      "--fde-ocean-700": "color",
      "--fde-white": "color",
      "--fde-paper": "color",
      "--fde-mist": "color",
      "--fde-line": "color",
      "--fde-gray-300": "color",
      "--fde-gray-400": "color",
      "--fde-slate": "color",
      "--fde-slate-700": "color",
      "--fde-ink": "color",
      "--fde-success": "color",
      "--fde-warning": "color",
      "--fde-danger": "color",
      "--fde-info": "color",
      "--color-primary": "color",
      "--color-primary-hover": "color",
      "--color-primary-active": "color",
      "--color-secondary": "color",
      "--color-secondary-hover": "color",
      "--color-accent": "color",
      "--color-deep": "color",
      "--text-strong": "font",
      "--text-heading": "font",
      "--text-body": "font",
      "--text-muted": "font",
      "--text-on-brand": "font",
      "--text-link": "font",
      "--surface-page": "color",
      "--surface-card": "color",
      "--surface-sunken": "color",
      "--surface-brand": "color",
      "--surface-deep": "color",
      "--border-subtle": "color",
      "--border-strong": "color",
      "--border-focus": "color",
      "--gradient-wave": "color",
      "--gradient-wave-soft": "color",
      "--gradient-deep": "color",
      "--font-display": "font",
      "--font-sans": "font",
      "--font-accent": "font",
      "--fw-regular": "font",
      "--fw-medium": "font",
      "--fw-semibold": "font",
      "--fw-bold": "font",
      "--fw-extra": "font",
      "--text-xs": "font",
      "--text-sm": "font",
      "--text-base": "font",
      "--text-md": "font",
      "--text-lg": "font",
      "--text-xl": "font",
      "--text-2xl": "font",
      "--text-3xl": "font",
      "--text-4xl": "font",
      "--text-5xl": "font",
      "--text-6xl": "font",
      "--leading-tight": "other",
      "--leading-snug": "other",
      "--leading-normal": "other",
      "--leading-relaxed": "other",
      "--tracking-tight": "font",
      "--tracking-normal": "font",
      "--tracking-wide": "font",
      "--tracking-caps": "font",
      "--tracking-wordmark": "font",
      "--display-font": "font",
      "--display-weight": "font",
      "--display-tracking": "font",
      "--heading-font": "font",
      "--heading-weight": "font",
      "--body-font": "font",
      "--body-weight": "font",
      "--eyebrow-font": "font",
      "--quote-font": "font",
      "--space-0": "spacing",
      "--space-1": "spacing",
      "--space-2": "spacing",
      "--space-3": "spacing",
      "--space-4": "spacing",
      "--space-5": "spacing",
      "--space-6": "spacing",
      "--space-7": "spacing",
      "--space-8": "spacing",
      "--space-9": "spacing",
      "--space-10": "spacing",
      "--space-12": "spacing",
      "--radius-xs": "radius",
      "--radius-sm": "radius",
      "--radius-md": "radius",
      "--radius-lg": "radius",
      "--radius-xl": "radius",
      "--radius-2xl": "radius",
      "--radius-pill": "radius",
      "--radius-circle": "radius",
      "--shadow-xs": "shadow",
      "--shadow-sm": "shadow",
      "--shadow-md": "shadow",
      "--shadow-lg": "shadow",
      "--shadow-brand": "shadow",
      "--ring-focus": "shadow",
      "--container-max": "spacing",
      "--container-narrow": "spacing",
      "--header-height": "spacing",
      "--ease-standard": "other",
      "--ease-out": "other",
      "--dur-fast": "other",
      "--dur-base": "other",
      "--dur-slow": "other"
    },
    "fontFamilies": [
      "Lora",
      "Mulish",
      "Oswald"
    ]
  }
}